{
  "id": "35253e94-7b50-42e4-a21a-cd153a8ebbe7",
  "prevId": "00000000-0000-0000-0000-000000000000",
  "version": "7",
  "dialect": "postgresql",
  "tables": {
    "public.decks": {
      "name": "decks",
      "schema": "",
      "columns": {
        "id": {
          "name": "id",
          "type": "uuid",
          "primaryKey": true,
          "notNull": true,
          "default": "gen_random_uuid()"
        },
        "user_id": {
          "name": "user_id",
          "type": "uuid",
          "primaryKey": false,
          "notNull": true
        },
        "title": {
          "name": "title",
          "type": "text",
          "primaryKey": false,
          "notNull": true
        },
        "created_at": {
          "name": "created_at",
          "type": "timestamp with time zone",
          "primaryKey": false,
          "notNull": true,
          "default": "now()"
        }
      },
      "indexes": {},
      "foreignKeys": {
        "decks_user_id_users_id_fk": {
          "name": "decks_user_id_users_id_fk",
          "tableFrom": "decks",
          "tableTo": "users",
          "columnsFrom": [
            "user_id"
          ],
          "columnsTo": [
            "id"
          ],
          "onDelete": "no action",
          "onUpdate": "no action"
        }
      },
      "compositePrimaryKeys": {},
      "uniqueConstraints": {},
      "policies": {},
      "checkConstraints": {},
      "isRLSEnabled": false
    },
    "public.evaluations": {
      "name": "evaluations",
      "schema": "",
      "columns": {
        "id": {
          "name": "id",
          "type": "uuid",
          "primaryKey": true,
          "notNull": true,
          "default": "gen_random_uuid()"
        },
        "user_id": {
          "name": "user_id",
          "type": "uuid",
          "primaryKey": false,
          "notNull": true
        },
        "question_id": {
          "name": "question_id",
          "type": "uuid",
          "primaryKey": false,
          "notNull": true
        },
        "user_answer": {
          "name": "user_answer",
          "type": "text",
          "primaryKey": false,
          "notNull": true
        },
        "score": {
          "name": "score",
          "type": "integer",
          "primaryKey": false,
          "notNull": true
        },
        "covered": {
          "name": "covered",
          "type": "jsonb",
          "primaryKey": false,
          "notNull": true
        },
        "missing": {
          "name": "missing",
          "type": "jsonb",
          "primaryKey": false,
          "notNull": true
        },
        "tip": {
          "name": "tip",
          "type": "text",
          "primaryKey": false,
          "notNull": true
        },
        "latency_ms": {
          "name": "latency_ms",
          "type": "integer",
          "primaryKey": false,
          "notNull": true
        },
        "created_at": {
          "name": "created_at",
          "type": "timestamp with time zone",
          "primaryKey": false,
          "notNull": true,
          "default": "now()"
        }
      },
      "indexes": {},
      "foreignKeys": {
        "evaluations_user_id_users_id_fk": {
          "name": "evaluations_user_id_users_id_fk",
          "tableFrom": "evaluations",
          "tableTo": "users",
          "columnsFrom": [
            "user_id"
          ],
          "columnsTo": [
            "id"
          ],
          "onDelete": "no action",
          "onUpdate": "no action"
        },
        "evaluations_question_id_questions_id_fk": {
          "name": "evaluations_question_id_questions_id_fk",
          "tableFrom": "evaluations",
          "tableTo": "questions",
          "columnsFrom": [
            "question_id"
          ],
          "columnsTo": [
            "id"
          ],
          "onDelete": "no action",
          "onUpdate": "no action"
        }
      },
      "compositePrimaryKeys": {},
      "uniqueConstraints": {},
      "policies": {},
      "checkConstraints": {},
      "isRLSEnabled": false
    },
    "public.modules": {
      "name": "modules",
      "schema": "",
      "columns": {
        "id": {
          "name": "id",
          "type": "uuid",
          "primaryKey": true,
          "notNull": true,
          "default": "gen_random_uuid()"
        },
        "deck_id": {
          "name": "deck_id",
          "type": "uuid",
          "primaryKey": false,
          "notNull": true
        },
        "number": {
          "name": "number",
          "type": "integer",
          "primaryKey": false,
          "notNull": true
        },
        "title": {
          "name": "title",
          "type": "text",
          "primaryKey": false,
          "notNull": true
        },
        "short_label": {
          "name": "short_label",
          "type": "text",
          "primaryKey": false,
          "notNull": false
        },
        "color": {
          "name": "color",
          "type": "text",
          "primaryKey": false,
          "notNull": false
        },
        "created_at": {
          "name": "created_at",
          "type": "timestamp with time zone",
          "primaryKey": false,
          "notNull": true,
          "default": "now()"
        }
      },
      "indexes": {},
      "foreignKeys": {
        "modules_deck_id_decks_id_fk": {
          "name": "modules_deck_id_decks_id_fk",
          "tableFrom": "modules",
          "tableTo": "decks",
          "columnsFrom": [
            "deck_id"
          ],
          "columnsTo": [
            "id"
          ],
          "onDelete": "no action",
          "onUpdate": "no action"
        }
      },
      "compositePrimaryKeys": {},
      "uniqueConstraints": {},
      "policies": {},
      "checkConstraints": {},
      "isRLSEnabled": false
    },
    "public.progress": {
      "name": "progress",
      "schema": "",
      "columns": {
        "id": {
          "name": "id",
          "type": "uuid",
          "primaryKey": true,
          "notNull": true,
          "default": "gen_random_uuid()"
        },
        "user_id": {
          "name": "user_id",
          "type": "uuid",
          "primaryKey": false,
          "notNull": true
        },
        "question_id": {
          "name": "question_id",
          "type": "uuid",
          "primaryKey": false,
          "notNull": true
        },
        "status": {
          "name": "status",
          "type": "text",
          "primaryKey": false,
          "notNull": true,
          "default": "'new'"
        },
        "times_seen": {
          "name": "times_seen",
          "type": "integer",
          "primaryKey": false,
          "notNull": true,
          "default": 0
        },
        "times_correct": {
          "name": "times_correct",
          "type": "integer",
          "primaryKey": false,
          "notNull": true,
          "default": 0
        },
        "last_seen_at": {
          "name": "last_seen_at",
          "type": "timestamp with time zone",
          "primaryKey": false,
          "notNull": false
        }
      },
      "indexes": {},
      "foreignKeys": {
        "progress_user_id_users_id_fk": {
          "name": "progress_user_id_users_id_fk",
          "tableFrom": "progress",
          "tableTo": "users",
          "columnsFrom": [
            "user_id"
          ],
          "columnsTo": [
            "id"
          ],
          "onDelete": "no action",
          "onUpdate": "no action"
        },
        "progress_question_id_questions_id_fk": {
          "name": "progress_question_id_questions_id_fk",
          "tableFrom": "progress",
          "tableTo": "questions",
          "columnsFrom": [
            "question_id"
          ],
          "columnsTo": [
            "id"
          ],
          "onDelete": "no action",
          "onUpdate": "no action"
        }
      },
      "compositePrimaryKeys": {},
      "uniqueConstraints": {
        "progress_user_question_unique": {
          "name": "progress_user_question_unique",
          "nullsNotDistinct": false,
          "columns": [
            "user_id",
            "question_id"
          ]
        }
      },
      "policies": {},
      "checkConstraints": {
        "progress_status_check": {
          "name": "progress_status_check",
          "value": "\"progress\".\"status\" in ('new', 'weak', 'learning', 'mastered')"
        }
      },
      "isRLSEnabled": false
    },
    "public.questions": {
      "name": "questions",
      "schema": "",
      "columns": {
        "id": {
          "name": "id",
          "type": "uuid",
          "primaryKey": true,
          "notNull": true,
          "default": "gen_random_uuid()"
        },
        "module_id": {
          "name": "module_id",
          "type": "uuid",
          "primaryKey": false,
          "notNull": true
        },
        "kind": {
          "name": "kind",
          "type": "text",
          "primaryKey": false,
          "notNull": true,
          "default": "'question'"
        },
        "prompt": {
          "name": "prompt",
          "type": "text",
          "primaryKey": false,
          "notNull": true
        },
        "model_answer": {
          "name": "model_answer",
          "type": "text",
          "primaryKey": false,
          "notNull": true
        },
        "short_answer": {
          "name": "short_answer",
          "type": "text",
          "primaryKey": false,
          "notNull": false
        },
        "created_at": {
          "name": "created_at",
          "type": "timestamp with time zone",
          "primaryKey": false,
          "notNull": true,
          "default": "now()"
        }
      },
      "indexes": {},
      "foreignKeys": {
        "questions_module_id_modules_id_fk": {
          "name": "questions_module_id_modules_id_fk",
          "tableFrom": "questions",
          "tableTo": "modules",
          "columnsFrom": [
            "module_id"
          ],
          "columnsTo": [
            "id"
          ],
          "onDelete": "no action",
          "onUpdate": "no action"
        }
      },
      "compositePrimaryKeys": {},
      "uniqueConstraints": {},
      "policies": {},
      "checkConstraints": {
        "questions_kind_check": {
          "name": "questions_kind_check",
          "value": "\"questions\".\"kind\" in ('question', 'term')"
        }
      },
      "isRLSEnabled": false
    },
    "public.usage_counters": {
      "name": "usage_counters",
      "schema": "",
      "columns": {
        "id": {
          "name": "id",
          "type": "uuid",
          "primaryKey": true,
          "notNull": true,
          "default": "gen_random_uuid()"
        },
        "user_id": {
          "name": "user_id",
          "type": "uuid",
          "primaryKey": false,
          "notNull": true
        },
        "period": {
          "name": "period",
          "type": "text",
          "primaryKey": false,
          "notNull": true
        },
        "ai_grades": {
          "name": "ai_grades",
          "type": "integer",
          "primaryKey": false,
          "notNull": true,
          "default": 0
        }
      },
      "indexes": {},
      "foreignKeys": {
        "usage_counters_user_id_users_id_fk": {
          "name": "usage_counters_user_id_users_id_fk",
          "tableFrom": "usage_counters",
          "tableTo": "users",
          "columnsFrom": [
            "user_id"
          ],
          "columnsTo": [
            "id"
          ],
          "onDelete": "no action",
          "onUpdate": "no action"
        }
      },
      "compositePrimaryKeys": {},
      "uniqueConstraints": {
        "usage_counters_user_period_unique": {
          "name": "usage_counters_user_period_unique",
          "nullsNotDistinct": false,
          "columns": [
            "user_id",
            "period"
          ]
        }
      },
      "policies": {},
      "checkConstraints": {},
      "isRLSEnabled": false
    },
    "public.users": {
      "name": "users",
      "schema": "",
      "columns": {
        "id": {
          "name": "id",
          "type": "uuid",
          "primaryKey": true,
          "notNull": true
        },
        "email": {
          "name": "email",
          "type": "text",
          "primaryKey": false,
          "notNull": true
        },
        "plan": {
          "name": "plan",
          "type": "text",
          "primaryKey": false,
          "notNull": true,
          "default": "'free'"
        },
        "created_at": {
          "name": "created_at",
          "type": "timestamp with time zone",
          "primaryKey": false,
          "notNull": true,
          "default": "now()"
        }
      },
      "indexes": {},
      "foreignKeys": {},
      "compositePrimaryKeys": {},
      "uniqueConstraints": {
        "users_email_unique": {
          "name": "users_email_unique",
          "nullsNotDistinct": false,
          "columns": [
            "email"
          ]
        }
      },
      "policies": {},
      "checkConstraints": {},
      "isRLSEnabled": false
    }
  },
  "enums": {},
  "schemas": {},
  "sequences": {},
  "roles": {},
  "policies": {},
  "views": {},
  "_meta": {
    "columns": {},
    "schemas": {},
    "tables": {}
  }
}